python_search/.DS_Store
python_search/__init__.py
python_search/apps/README.md
python_search/apps/__init__.py
python_search/apps/apps.py
python_search/apps/browser.py
python_search/apps/clipboard.py
python_search/apps/collect_input.py
python_search/apps/google_it.py
python_search/apps/notification_ui.py
python_search/apps/terminal.py
python_search/apps/theme/BaseTheme.py
python_search/apps/theme/ThemeSelector.py
python_search/apps/theme/__init__.py
python_search/apps/theme/theme.py
python_search/apps/window_manager.py
python_search/configuration/__init__.py
python_search/configuration/configuration.py
python_search/configuration/data_config.py
python_search/configuration/loader.py
python_search/context.py
python_search/core_entities.py
python_search/declarative_ui/__init__.py
python_search/declarative_ui/declarative_ui.py
python_search/entries_group.py
python_search/entry_capture/__init__.py
python_search/entry_capture/ask_question_ui.py
python_search/entry_capture/entries_editor.py
python_search/entry_capture/filesystem_entry_inserter.py
python_search/entry_capture/register_new.py
python_search/entry_change.py
python_search/entry_runner.py
python_search/environment.py
python_search/error/__init__.py
python_search/error/error_pane.py
python_search/error/exception.py
python_search/events/__init__.py
python_search/events/data_collector.py
python_search/events/events_etl.py
python_search/events/latest_used_entries.py
python_search/events/ranking_generated/__init__.py
python_search/events/run_performed/__init__.py
python_search/events/run_performed/clean.py
python_search/events/run_performed/dataset.py
python_search/events/run_performed/entity.py
python_search/events/run_performed/writer.py
python_search/exceptions.py
python_search/host_system/__init__.py
python_search/host_system/system_paths.py
python_search/host_system/window_hide.py
python_search/host_system/windows_focus.py
python_search/init/entries_main.py
python_search/init/install_dependencies.py
python_search-0.51.dist-info/METADATA
python_search-0.51.dist-info/WHEEL
python_search-0.51.dist-info/entry_points.txt
python_search-0.51.dist-info/licenses/LICENSE
python_search-0.51.dist-info/licenses/NOTICE.md
python_search-0.51.dist-info/RECORD
