Metadata-Version: 2.4
Name: python-search
Version: 0.51
Summary: Build your knowledge database in python and retrieve it efficiently
License-File: LICENSE
License-File: NOTICE.md
Author: Jean Carlo Machado
Author-email: machado.c.jean@gmail.com
Requires-Python: >=3.10,<=3.14
Classifier: Programming Language :: Python :: 3
Classifier: Programming Language :: Python :: 3.10
Classifier: Programming Language :: Python :: 3.11
Classifier: Programming Language :: Python :: 3.12
Classifier: Programming Language :: Python :: 3.13
Classifier: Programming Language :: Python :: 3.14
Requires-Dist: PySimpleGUI
Requires-Dist: PyYAML (>=6.0,<7.0)
Requires-Dist: certifi (>=2022.6.1)
Requires-Dist: chardet (>=5.1.0,<6.0.0)
Requires-Dist: chromadb (>=0.5.0)
Requires-Dist: colorama (>=0.4.5,<0.5.0)
Requires-Dist: colorful (>=0.5.5,<0.6.0)
Requires-Dist: datadog
Requires-Dist: dill (>=0.3.5.1,<0.4.0.0)
Requires-Dist: fire (>=0.6)
Requires-Dist: nltk (>=3.9.1,<4.0.0)
Requires-Dist: openai (>=0.27.0)
Requires-Dist: openapi (>=1.1.0,<2.0.0)
Requires-Dist: pydantic
Requires-Dist: python-daemon (>=3.0.1,<4.0.0)
Requires-Dist: python-dateutil (>=2.8.2,<3.0.0)
Requires-Dist: rank-bm25 (>=0.2.2,<0.3.0)
Requires-Dist: schedule (>=1.2.1,<2.0.0)
Requires-Dist: tiny-data-warehouse (>=0.1.5)
